ptpt/__init__.py
ptpt/callbacks.py
ptpt/log.py
ptpt/scheduling.py
ptpt/trainer.py
ptpt/utils.py
ptpt/wandb.py
ptpt-0.0.28.dist-info/LICENSE
ptpt-0.0.28.dist-info/METADATA
ptpt-0.0.28.dist-info/WHEEL
ptpt-0.0.28.dist-info/top_level.txt
ptpt-0.0.28.dist-info/RECORD
