Metadata-Version: 2.1
Name: ptpt
Version: 0.0.28
Summary: PyTorch Personal Trainer: My personal framework for deep learning experiments
Home-page: https://github.com/vvvm23/ptpt
Author: Alex McKinney
Author-email: alexander.f.mckinney@durham.ac.uk
License: MIT License
Keywords: artificial intelligence,deep learning,pytorch
Classifier: Programming Language :: Python :: 3
Classifier: License :: OSI Approved :: MIT License
Classifier: Operating System :: OS Independent
Requires-Python: >=3.7
License-File: LICENSE
Requires-Dist: torch
Requires-Dist: rich
Requires-Dist: wandb
Requires-Dist: accelerate
